asim/__init__.py
asim/convert.cp313-win_amd64.pyd
asim/dataset.cp313-win_amd64.pyd
asim/dataset.pyi
asim/explainer.cp313-win_amd64.pyd
asim/model.cp313-win_amd64.pyd
asim/model.pyi
asim/optimizer.cp313-win_amd64.pyd
asim/optimizer.pyi
asim/simulator.cp313-win_amd64.pyd
asim/simulator.pyi
asim/version.py
asim-26.1.6.dist-info/licenses/LICENSE
asim-26.1.6.dist-info/METADATA
asim-26.1.6.dist-info/WHEEL
asim-26.1.6.dist-info/top_level.txt
asim-26.1.6.dist-info/RECORD
