Metadata-Version: 2.4
Name: asim
Version: 26.1.6
Summary: Automatic simulation system powered by neural networks
Keywords: simulation
Requires-Python: >=3.12
License-File: LICENSE
Requires-Dist: torch>=2.8.0
Requires-Dist: lightning>=2.5.5
Requires-Dist: casadi>=3.7.2
Provides-Extra: dev
Requires-Dist: matplotlib; extra == "dev"
Dynamic: license-file
